py_uds_lib/__init__.py
py_uds_lib/py_uds_lib.py
py_uds_lib-25.0.1.dist-info/WHEEL
py_uds_lib-25.0.1.dist-info/METADATA
py_uds_lib-25.0.1.dist-info/RECORD
