Metadata-Version: 2.3
Name: py-uds-lib
Version: 25.0.1
Summary: Python package for creating UDS requests
Keywords: python,UDS,diagnostics
Author: chaitu-ycr
Author-email: chaitu-ycr <chaitu.ycr@gmail.com>
License: MIT License
Classifier: Programming Language :: Python :: 3
Classifier: License :: OSI Approved :: MIT License
Classifier: Operating System :: Microsoft :: Windows
Classifier: Topic :: Software Development :: Embedded Systems
Requires-Dist: cantools
Requires-Dist: odxtools
Requires-Dist: python-can
Requires-Python: >=3.10, <=3.14
Project-URL: documentation, https://chaitu-ycr.github.io/automotive-test-kit/packages/py_uds_lib
Project-URL: homepage, https://github.com/chaitu-ycr/automotive-test-kit/tree/main/packages/py_uds_lib
Project-URL: repository, https://github.com/chaitu-ycr/automotive-test-kit
